jackalify/__init__.py
jackalify/__main__.py
jackalify/app.py
jackalify/jackal.py
jackalify/seam_carve.py
jackalify/locales/en/LC_MESSAGES/jackalify.mo
jackalify/locales/ru/LC_MESSAGES/jackalify.mo
jackalify/static/css/style.css
jackalify/static/images/bottle.jpg
jackalify/static/js/scripts.js
jackalify/templates/main_form.html
jackalify-0.2.5.dist-info/LICENSE
jackalify-0.2.5.dist-info/METADATA
jackalify-0.2.5.dist-info/WHEEL
jackalify-0.2.5.dist-info/entry_points.txt
jackalify-0.2.5.dist-info/top_level.txt
jackalify-0.2.5.dist-info/RECORD
