Metadata-Version: 2.1
Name: jackalify
Version: 0.2.5
Summary: Jackalifying pictures!
Home-page: https://github.com/Sea-Bottle/Sea-Bottle-Jackal
Author: Max Raenchuk, Anastasiya Bogatenkova, Yaroslav Zykin, Ilya Mushkin
Classifier: Framework :: FastAPI
Classifier: Programming Language :: Python :: 3
License-File: LICENSE
Requires-Dist: opencv-python
Requires-Dist: aiofiles
Requires-Dist: fastapi
Requires-Dist: tqdm
Requires-Dist: pillow
Requires-Dist: jinja2
Requires-Dist: python-multipart
Requires-Dist: uvicorn
